README.rst
setup.py
pylc3.autograder.egg-info/PKG-INFO
pylc3.autograder.egg-info/SOURCES.txt
pylc3.autograder.egg-info/dependency_links.txt
pylc3.autograder.egg-info/requires.txt
pylc3.autograder.egg-info/top_level.txt
pylc3/autograder/__init__.py
pylc3/autograder/lc3_unit_test_case.py
pylc3/autograder/test_lc3_unit_test_case.py