Metadata-Version: 2.1
Name: pylc3.autograder
Version: 0.2.1
Summary: Autograder and Unit testing framework for LC-3 code written in Python, exports test results in JSON.
Home-page: https://github.com/complx-tools/pylc3.autograder
Author: Brandon Whitehead
Author-email: brandon.whitehead@gatech.edu
License: GNU General Public License v3
Platform: UNKNOWN
